logger_hub_pmf/__init__.py
logger_hub_pmf/logger_utils.py
logger_hub_pmf-0.1.0.dist-info/WHEEL
logger_hub_pmf-0.1.0.dist-info/METADATA
logger_hub_pmf-0.1.0.dist-info/RECORD
