Metadata-Version: 2.1
Name: logger-hub-pmf
Version: 0.1.0
Summary: 
Author: Pablo Martin Fernandez
Author-email: pablo.martin.fernandez@pwc.com
Requires-Python: >=3.9,<4.0
Classifier: Programming Language :: Python :: 3
Classifier: Programming Language :: Python :: 3.9
Requires-Dist: requests (>=2.28.1,<3.0.0)
